vantage_sdk/__init__.py
vantage_sdk/client.py
vantage_sdk/config.py
vantage_sdk/core/__init__.py
vantage_sdk/core/base.py
vantage_sdk/core/exceptions.py
vantage_sdk/core/http/__init__.py
vantage_sdk/core/http/api/__init__.py
vantage_sdk/core/http/api/account_management_api.py
vantage_sdk/core/http/api/collection_management_api.py
vantage_sdk/core/http/api/documents_api.py
vantage_sdk/core/http/api/external_keys_api.py
vantage_sdk/core/http/api/search_api.py
vantage_sdk/core/http/api/shopping_assistant_api.py
vantage_sdk/core/http/api/vantage_api_keys_api.py
vantage_sdk/core/http/api/vantage_vibe_api.py
vantage_sdk/core/http/api_client.py
vantage_sdk/core/http/api_response.py
vantage_sdk/core/http/configuration.py
vantage_sdk/core/http/exceptions.py
vantage_sdk/core/http/models/__init__.py
vantage_sdk/core/http/models/account.py
vantage_sdk/core/http/models/account_modifiable.py
vantage_sdk/core/http/models/account_read_only.py
vantage_sdk/core/http/models/collection.py
vantage_sdk/core/http/models/collection_immutable.py
vantage_sdk/core/http/models/collection_modifiable.py
vantage_sdk/core/http/models/collection_read_only.py
vantage_sdk/core/http/models/collection_status.py
vantage_sdk/core/http/models/collection_status_ingest_statuses_inner.py
vantage_sdk/core/http/models/collection_upload_url.py
vantage_sdk/core/http/models/create_collection_request.py
vantage_sdk/core/http/models/document_batch.py
vantage_sdk/core/http/models/embedding_search_query.py
vantage_sdk/core/http/models/external_key.py
vantage_sdk/core/http/models/external_key_modifiable.py
vantage_sdk/core/http/models/external_key_read_only.py
vantage_sdk/core/http/models/facet_range.py
vantage_sdk/core/http/models/facet_result.py
vantage_sdk/core/http/models/ml_these.py
vantage_sdk/core/http/models/ml_these_these_inner.py
vantage_sdk/core/http/models/more_like_these_query.py
vantage_sdk/core/http/models/more_like_this_query.py
vantage_sdk/core/http/models/search_options.py
vantage_sdk-0.9.5.dist-info/LICENSE
vantage_sdk-0.9.5.dist-info/METADATA
vantage_sdk-0.9.5.dist-info/WHEEL
vantage_sdk-0.9.5.dist-info/RECORD
