Metadata-Version: 2.1
Name: vantage-sdk
Version: 0.9.5
Summary: Vantage Python SDK.
Home-page: https://github.com/VantageDiscovery/vantage-sdk-python
Author: Vantage
Author-email: none@vantage.com
Requires-Python: >=3.10
Classifier: Programming Language :: Python :: 3
Classifier: Programming Language :: Python :: 3.10
Classifier: Programming Language :: Python :: 3.11
Classifier: Programming Language :: Python :: 3.12
Classifier: Programming Language :: Python :: 3.13
Provides-Extra: dev
Provides-Extra: doc
Provides-Extra: publish
Provides-Extra: test
Requires-Dist: black (>=23.0,<24.0) ; extra == "test"
Requires-Dist: bump2version (>=1.0.1,<2.0.0) ; extra == "dev"
Requires-Dist: bumpver (>=2023.1129) ; extra == "dev"
Requires-Dist: flake8 (>=5.0.1,<6.0.0) ; extra == "test"
Requires-Dist: flake8-docstrings (>=1.6.0,<2.0.0) ; extra == "test"
Requires-Dist: flake8-pyproject (>=1.2.3,<2.0.0) ; extra == "test"
Requires-Dist: griffe-fieldz (>=0.1.2)
Requires-Dist: isort (>=5.8.0,<6.0.0) ; extra == "test"
Requires-Dist: mkdocs (>=1.6.0,<2.0.0) ; extra == "doc"
Requires-Dist: mkdocs-include-markdown-plugin (>=6.0.6,<7.0.0) ; extra == "doc"
Requires-Dist: mkdocs-material (>=9.5.23,<10.0.0) ; extra == "doc"
Requires-Dist: mkdocstrings[python] (>=0.25.1)
Requires-Dist: mypy (>=1.5,<2.0) ; extra == "test"
Requires-Dist: pandas (>=2.2.2,<3.0.0)
Requires-Dist: pip ; extra == "dev"
Requires-Dist: pip-tools (>=7.3.0) ; extra == "dev"
Requires-Dist: pre-commit (>=3.3.0,<4.0.0) ; extra == "dev"
Requires-Dist: pyarrow (>=16.1.0)
Requires-Dist: pydantic (>=2)
Requires-Dist: pytest (>=7.2.0,<8.0.0) ; extra == "test"
Requires-Dist: pytest-cov (>=4.0.0,<5.0.0) ; extra == "test"
Requires-Dist: pytest-env (>=1.1.3) ; extra == "test"
Requires-Dist: python-dateutil (>=2,<3)
Requires-Dist: python-dotenv (>=1.0.1) ; extra == "dev"
Requires-Dist: python-magic (>=0.4,<=0.5)
Requires-Dist: requests (>=2,<3)
Requires-Dist: tiktoken (>=0.7.0)
Requires-Dist: toml (>=0.10.2,<0.11.0) ; extra == "dev"
Requires-Dist: tox (>=4.0.0,<5.0.0) ; extra == "dev"
Requires-Dist: twine (>=4.0.2,<5.0.0) ; extra == "publish"
Requires-Dist: urllib3 (>=2,<3)
Requires-Dist: virtualenv (>=20.2.2,<21.0.0) ; extra == "dev"
Project-URL: Documentation, https://docs.vantagediscovery.com/docs/concepts
Project-URL: Repository, https://github.com/VantageDiscovery/vantage-sdk-python
